{"_ts":[1546332536],"_r":{"breakdown":{"html":{"bytes":[97138],"requests":[7]},"js":{"bytes":[352021],"requests":[16]},"css":{"bytes":[149520],"requests":[4]},"image":{"bytes":[316611],"requests":[20]},"flash":{"bytes":[0],"requests":[0]},"font":{"bytes":[280286],"requests":[4]},"video":{"bytes":[0],"requests":[0]},"other":{"bytes":[3937],"requests":[5]}},"date":[1546332536],"domElements":[1868],"domInteractive":[8028],"firstPaint":[6522.1999999994],"fullyLoaded":[9898],"id":["190101_FN_ec541c4a2b7a59ca5f257aed2b389d41"],"loadTime":[9283],"render":[6500],"SpeedIndex":[6923],"TTFB":[6091],"videoFrames":[[{"_i":"ms_000000.jpg","_t":0,"_vc":0},{"_i":"ms_006500.jpg","_t":6500,"_vc":32},{"_i":"ms_006600.jpg","_t":6600,"_vc":32},{"_i":"ms_006700.jpg","_t":6700,"_vc":42},{"_i":"ms_006800.jpg","_t":6800,"_vc":40},{"_i":"ms_006900.jpg","_t":6900,"_vc":83},{"_i":"ms_007000.jpg","_t":7000,"_vc":83},{"_i":"ms_007300.jpg","_t":7300,"_vc":85},{"_i":"ms_007400.jpg","_t":7400,"_vc":84},{"_i":"ms_007500.jpg","_t":7500,"_vc":84},{"_i":"ms_007600.jpg","_t":7600,"_vc":85},{"_i":"ms_007800.jpg","_t":7800,"_vc":94},{"_i":"ms_007900.jpg","_t":7900,"_vc":94},{"_i":"ms_008200.jpg","_t":8200,"_vc":100}]],"visualComplete":[8200],"lighthouse":[42],"pagespeed":[62]}}