{"_ts":[1520271696],"_r":{"breakdown":{"html":{"bytes":[64389],"requests":[8]},"js":{"bytes":[674384],"requests":[35]},"css":{"bytes":[156870],"requests":[6]},"image":{"bytes":[1204209],"requests":[30]},"flash":{"bytes":[0],"requests":[0]},"font":{"bytes":[199989],"requests":[8]},"video":{"bytes":[182187],"requests":[1]},"other":{"bytes":[12924],"requests":[11]}},"date":[1520271696],"domElements":[2095],"domInteractive":[10825],"firstPaint":[8876.4999999985],"fullyLoaded":[48245],"id":["180305_PR_15b63a2ce742d69ba3630df1eecf0b75"],"loadTime":[46759],"render":[8900],"SpeedIndex":[11989],"TTFB":[8206],"videoFrames":[[{"_i":"ms_000000.jpg","_t":0,"_vc":0},{"_i":"ms_008900.jpg","_t":8900,"_vc":12},{"_i":"ms_009100.jpg","_t":9100,"_vc":12},{"_i":"ms_009300.jpg","_t":9300,"_vc":16},{"_i":"ms_009500.jpg","_t":9500,"_vc":17},{"_i":"ms_009700.jpg","_t":9700,"_vc":29},{"_i":"ms_010000.jpg","_t":10000,"_vc":29},{"_i":"ms_010300.jpg","_t":10300,"_vc":29},{"_i":"ms_011600.jpg","_t":11600,"_vc":48},{"_i":"ms_011800.jpg","_t":11800,"_vc":48},{"_i":"ms_011900.jpg","_t":11900,"_vc":47},{"_i":"ms_012000.jpg","_t":12000,"_vc":47},{"_i":"ms_012600.jpg","_t":12600,"_vc":79},{"_i":"ms_012700.jpg","_t":12700,"_vc":81},{"_i":"ms_013600.jpg","_t":13600,"_vc":100},{"_i":"ms_013800.jpg","_t":13800,"_vc":99},{"_i":"ms_014000.jpg","_t":14000,"_vc":99},{"_i":"ms_022300.jpg","_t":22300,"_vc":99},{"_i":"ms_022500.jpg","_t":22500,"_vc":99},{"_i":"ms_046800.jpg","_t":46800,"_vc":99},{"_i":"ms_047100.jpg","_t":47100,"_vc":99},{"_i":"ms_047200.jpg","_t":47200,"_vc":99},{"_i":"ms_047300.jpg","_t":47300,"_vc":100}]],"visualComplete":[13600],"lighthouse":[27],"pagespeed":[75]}}