{"_ts":[1546370341,1546414186],"_r":{"breakdown":{"html":{"bytes":[105716,105716],"requests":[5,5]},"js":{"bytes":[692832,692829],"requests":[34,34]},"css":{"bytes":[193095,193095],"requests":[5,5]},"image":{"bytes":[532700,532708],"requests":[34,34]},"flash":{"bytes":[0,0],"requests":[0,0]},"font":{"bytes":[259995,259995],"requests":[10,10]},"video":{"bytes":[442567,442567],"requests":[1,1]},"other":{"bytes":[27897,27873],"requests":[23,23]}},"date":[1546370341,1546414186],"domElements":[2595,2595],"domInteractive":[3299,3318],"firstPaint":[1372.74999999865,1274.84999999755],"fullyLoaded":[8949.5,8965],"id":["190101_P0_2763ad027529a560c967562a8d148913","190102_WJ_bba678d768c9c3ed686e8e1f526fa1ba"],"loadTime":[5476,5428.5],"render":[1350,1300],"SpeedIndex":[1940.5,1884],"TTFB":[592,521],"videoFrames":[[{"_i":"ms_000000.jpg","_t":0,"_vc":0},{"_i":"ms_001500.jpg","_t":1500,"_vc":10},{"_i":"ms_001600.jpg","_t":1600,"_vc":10},{"_i":"ms_001900.jpg","_t":1900,"_vc":11},{"_i":"ms_002200.jpg","_t":2200,"_vc":99},{"_i":"ms_002400.jpg","_t":2400,"_vc":99},{"_i":"ms_002800.jpg","_t":2800,"_vc":100},{"_i":"ms_003000.jpg","_t":3000,"_vc":100},{"_i":"ms_003700.jpg","_t":3700,"_vc":100}],[{"_i":"ms_000000.jpg","_t":0,"_vc":0},{"_i":"ms_001200.jpg","_t":1200,"_vc":8},{"_i":"ms_001300.jpg","_t":1300,"_vc":10},{"_i":"ms_001400.jpg","_t":1400,"_vc":12},{"_i":"ms_001700.jpg","_t":1700,"_vc":13},{"_i":"ms_001800.jpg","_t":1800,"_vc":14},{"_i":"ms_001900.jpg","_t":1900,"_vc":14},{"_i":"ms_002000.jpg","_t":2000,"_vc":13},{"_i":"ms_002100.jpg","_t":2100,"_vc":99},{"_i":"ms_002400.jpg","_t":2400,"_vc":99},{"_i":"ms_002800.jpg","_t":2800,"_vc":100},{"_i":"ms_002900.jpg","_t":2900,"_vc":100},{"_i":"ms_003300.jpg","_t":3300,"_vc":100},{"_i":"ms_003400.jpg","_t":3400,"_vc":99},{"_i":"ms_003500.jpg","_t":3500,"_vc":100},{"_i":"ms_003700.jpg","_t":3700,"_vc":100}]],"visualComplete":[2650,2800],"lighthouse":[31,31],"pagespeed":[63,63]}}