{"_ts":[1567298842],"_r":{"breakdown":{"html":{"bytes":[69586],"requests":[5]},"js":{"bytes":[369121],"requests":[25]},"css":{"bytes":[67314],"requests":[3]},"image":{"bytes":[382156],"requests":[34]},"flash":{"bytes":[0],"requests":[0]},"font":{"bytes":[160716],"requests":[6]},"video":{"bytes":[0],"requests":[0]},"other":{"bytes":[11430],"requests":[16]}},"date":[1567298842],"domElements":[1662],"domInteractive":[2391.5],"firstPaint":[1617.4000000032502],"fullyLoaded":[4993],"id":["190901_7G_13d61aa459fc65f406cfc35fe02b1565"],"loadTime":[4189.5],"render":[1650],"SpeedIndex":[2359.5],"TTFB":[818.5],"videoFrames":[[{"_i":"ms_000000.jpg","_t":0,"_vc":0},{"_i":"ms_001600.jpg","_t":1600,"_vc":17},{"_i":"ms_001800.jpg","_t":1800,"_vc":30},{"_i":"ms_002100.jpg","_t":2100,"_vc":32},{"_i":"ms_002300.jpg","_t":2300,"_vc":94},{"_i":"ms_002400.jpg","_t":2400,"_vc":94},{"_i":"ms_002500.jpg","_t":2500,"_vc":94},{"_i":"ms_003000.jpg","_t":3000,"_vc":93},{"_i":"ms_003100.jpg","_t":3100,"_vc":100}]],"visualComplete":[3350],"lighthouse":[31],"pagespeed":[76]}}