{"_ts":[1538423393,1538506607],"_r":{"breakdown":{"html":{"bytes":[114299,115478],"requests":[8,8]},"js":{"bytes":[338097,338077],"requests":[16,16]},"css":{"bytes":[150226,150226],"requests":[4,4]},"image":{"bytes":[320374,320374],"requests":[20,20]},"flash":{"bytes":[0,0],"requests":[0,0]},"font":{"bytes":[264942,264942],"requests":[3,3]},"video":{"bytes":[0,0],"requests":[0,0]},"other":{"bytes":[8333,6342],"requests":[9,8]}},"date":[1538423393,1538506607],"domElements":[1884,1884],"domInteractive":[13595,7639],"firstPaint":[12265.299999999,6136.0999999997],"fullyLoaded":[15528,9321],"id":["181001_8X_06f29921bc591fb28bb716f728b5eea4","181002_B8_c8b791e115f8f2f9f38a57e06451407b"],"loadTime":[14781,8611],"render":[12200,6200],"SpeedIndex":[12748,6731],"TTFB":[11586,5649],"videoFrames":[[{"_i":"ms_000000.jpg","_t":0,"_vc":0},{"_i":"ms_012200.jpg","_t":12200,"_vc":32},{"_i":"ms_012400.jpg","_t":12400,"_vc":15},{"_i":"ms_012500.jpg","_t":12500,"_vc":40},{"_i":"ms_012800.jpg","_t":12800,"_vc":83},{"_i":"ms_012900.jpg","_t":12900,"_vc":82},{"_i":"ms_013000.jpg","_t":13000,"_vc":82},{"_i":"ms_013200.jpg","_t":13200,"_vc":82},{"_i":"ms_013300.jpg","_t":13300,"_vc":84},{"_i":"ms_013400.jpg","_t":13400,"_vc":85},{"_i":"ms_013600.jpg","_t":13600,"_vc":94},{"_i":"ms_013800.jpg","_t":13800,"_vc":100}],[{"_i":"ms_000000.jpg","_t":0,"_vc":0},{"_i":"ms_006200.jpg","_t":6200,"_vc":32},{"_i":"ms_006300.jpg","_t":6300,"_vc":32},{"_i":"ms_006400.jpg","_t":6400,"_vc":39},{"_i":"ms_006800.jpg","_t":6800,"_vc":82},{"_i":"ms_007100.jpg","_t":7100,"_vc":83},{"_i":"ms_007200.jpg","_t":7200,"_vc":83},{"_i":"ms_007300.jpg","_t":7300,"_vc":84},{"_i":"ms_007500.jpg","_t":7500,"_vc":93},{"_i":"ms_007700.jpg","_t":7700,"_vc":95},{"_i":"ms_007800.jpg","_t":7800,"_vc":94},{"_i":"ms_008000.jpg","_t":8000,"_vc":100}]],"visualComplete":[13800,8000],"lighthouse":[42,42],"pagespeed":[56,67]}}