{"_ts":[1569935787,1569979010],"_r":{"breakdown":{"html":{"bytes":[55914,55819],"requests":[7,7]},"js":{"bytes":[651427,653664],"requests":[43,43]},"css":{"bytes":[149352,149767],"requests":[7,7]},"image":{"bytes":[133385,133385],"requests":[38,38]},"flash":{"bytes":[0,0],"requests":[0,0]},"font":{"bytes":[154096,154096],"requests":[5,5]},"video":{"bytes":[0,0],"requests":[0,0]},"other":{"bytes":[9524,9589],"requests":[17,18]}},"date":[1569935787,1569979010],"domElements":[1432,1432],"domInteractive":[1636,1719.5],"firstPaint":[1588.3124999964,1635.9575000006],"fullyLoaded":[6520,6426.5],"id":["191001_X4_1c71a27bca0c7628e019f0d448d2be64","191002_97_4b15b2e0946ce96260bb98466aa8099b"],"loadTime":[3899,3736],"render":[1600,1650],"SpeedIndex":[1831.5,1853],"TTFB":[479.5,457.5],"videoFrames":[[{"_i":"ms_000000.jpg","_t":0,"_vc":0},{"_i":"ms_001700.jpg","_t":1700,"_vc":32},{"_i":"ms_001800.jpg","_t":1800,"_vc":34},{"_i":"ms_002000.jpg","_t":2000,"_vc":95},{"_i":"ms_002100.jpg","_t":2100,"_vc":100}],[{"_i":"ms_000000.jpg","_t":0,"_vc":0},{"_i":"ms_001600.jpg","_t":1600,"_vc":34},{"_i":"ms_001900.jpg","_t":1900,"_vc":95},{"_i":"ms_002100.jpg","_t":2100,"_vc":100}]],"visualComplete":[2100,2050],"lighthouse":[27,27],"pagespeed":[72,72]}}