{"_ts":[1543643312],"_r":{"breakdown":{"html":{"bytes":[104384],"requests":[7]},"js":{"bytes":[601151],"requests":[30]},"css":{"bytes":[191215],"requests":[5]},"image":{"bytes":[134158],"requests":[32]},"flash":{"bytes":[0],"requests":[0]},"font":{"bytes":[294816],"requests":[11]},"video":{"bytes":[442176],"requests":[1]},"other":{"bytes":[20849],"requests":[19]}},"date":[1543643312],"domElements":[2476],"domInteractive":[3069],"firstPaint":[1412.2500000012],"fullyLoaded":[5726],"id":["181201_K2_04811606226cc634acd598600d12ec25"],"loadTime":[5318],"render":[1400],"SpeedIndex":[1588],"TTFB":[475],"videoFrames":[[{"_i":"ms_000000.jpg","_t":0,"_vc":0},{"_i":"ms_001500.jpg","_t":1500,"_vc":59},{"_i":"ms_002100.jpg","_t":2100,"_vc":99},{"_i":"ms_002400.jpg","_t":2400,"_vc":100}]],"visualComplete":[2200],"lighthouse":[31],"pagespeed":[null]}}